motty/db.sqlite3
motty/manage.py
motty/runmotty.py
motty/app/.DS_Store
motty/app/__init__.py
motty/app/admin.py
motty/app/apps.py
motty/app/models.py
motty/app/serializers.py
motty/app/tests.py
motty/app/urls.py
motty/app/utils.py
motty/app/views.py
motty/app/__pycache__/__init__.cpython-36.pyc
motty/app/__pycache__/admin.cpython-36.pyc
motty/app/__pycache__/models.cpython-36.pyc
motty/app/__pycache__/serializers.cpython-36.pyc
motty/app/__pycache__/urls.cpython-36.pyc
motty/app/__pycache__/utils.cpython-36.pyc
motty/app/__pycache__/views.cpython-36.pyc
motty/app/migrations/0001_initial.py
motty/app/migrations/0002_auto_20171118_0326.py
motty/app/migrations/0003_auto_20171118_0452.py
motty/app/migrations/0004_auto_20171118_0452.py
motty/app/migrations/0005_auto_20171208_1314.py
motty/app/migrations/__init__.py
motty/app/migrations/__pycache__/0001_initial.cpython-36.pyc
motty/app/migrations/__pycache__/0002_auto_20171118_0326.cpython-36.pyc
motty/app/migrations/__pycache__/0003_auto_20171118_0452.cpython-36.pyc
motty/app/migrations/__pycache__/0004_auto_20171118_0452.cpython-36.pyc
motty/app/migrations/__pycache__/0005_auto_20171208_1314.cpython-36.pyc
motty/app/migrations/__pycache__/__init__.cpython-36.pyc
motty/app/static/.DS_Store
motty/app/static/CACHE/css/main.080572c3c3d1.css
motty/app/static/CACHE/css/main.555924d5a3d3.css
motty/app/static/CACHE/css/main.b0b8dda050b2.css
motty/app/static/images/.DS_Store
motty/app/static/images/close.png
motty/app/static/images/empty_data.png
motty/app/static/images/github.png
motty/app/static/images/guide1.png
motty/app/static/images/mask.png
motty/app/static/images/motty.png
motty/app/static/images/github/detail.png
motty/app/static/images/github/main.png
motty/app/static/js/.DS_Store
motty/app/static/js/motty.js
motty/app/static/js/utils.js
motty/app/static/plugins/.DS_Store
motty/app/static/plugins/angularjs/.DS_Store
motty-1.0.6.dist-info/DESCRIPTION.rst
motty-1.0.6.dist-info/METADATA
motty-1.0.6.dist-info/RECORD
motty-1.0.6.dist-info/WHEEL
motty-1.0.6.dist-info/entry_points.txt
motty-1.0.6.dist-info/metadata.json
motty-1.0.6.dist-info/top_level.txt
