Metadata-Version: 2.0
Name: motty
Version: 1.0.6
Summary: Simpler way to build mocking http server. Do not code yourself for mocking!
Home-page: https://github.com/scalalang2/motty
Author: David Lee
Author-email: scalalang2@gmail.com
License: UNKNOWN
Keywords: mocking,motty,http
Platform: UNKNOWN
Requires-Dist: django
Requires-Dist: djangorestframework
Requires-Dist: django-libsass
Requires-Dist: libsass
Requires-Dist: django-compressor
Requires-Dist: django-sass-processor
Requires-Dist: tornado
